{
    "Pedro": {
        "cedulas": [
            {
                "titulo": "untitulo",
                "cedula": "11111"
            },
            {
                "titulo": "dostitulo",
                "cedula": "222222"
            },
            {
                "titulo": "trestitulo",
                "cedula": "333333"
            }
        ],
        "firma": "C:\\Users\\Naholyt\\Documents\\Ayax\\Veterinaria-Kaizen\\Firmas\\Pedro\\pfirma.jpg"
    },
    "Ayax Ortega Cordova": {
        "cedulas": [
            {
                "titulo": "Checador de sangre",
                "cedula": "12345"
            },
            {
                "titulo": "Checador de sangre",
                "cedula": "54321"
            }
        ],
        "firma": "C:\\Users\\Unbewohnt\\Documents\\Proyectos\\Veterinaria-Kaizen\\Firmas\\Ayax Ortega Cordova\\pfirma.jpg"
    },
    "Jesus sandoval": {
        "cedulas": [
            {
                "titulo": "Veterinario",
                "cedula": "12345"
            }
        ],
        "firma": "C:\\Users\\Unbewohnt\\Documents\\Proyectos\\Veterinaria-Kaizen\\Firmas\\Jesus sandoval\\pfirma.jpg"
    },
    "Sandre Ivette Cuevas": {
        "cedulas": [
            {
                "titulo": "Veterinaria",
                "cedula": "12345"
            }
        ],
        "firma": "C:\\Users\\Unbewohnt\\Documents\\Proyectos\\Veterinaria-Kaizen\\Firmas\\Sandre Ivette Cuevas\\pfirma.jpg"
    }
}